gordo/__init__.py
gordo/_version.py
gordo/utils.py
gordo/builder/__init__.py
gordo/builder/build_model.py
gordo/builder/local_build.py
gordo/builder/utils.py
gordo/cli/__init__.py
gordo/cli/cli.py
gordo/cli/custom_types.py
gordo/cli/exceptions_reporter.py
gordo/cli/workflow_generator.py
gordo/machine/__init__.py
gordo/machine/constants.py
gordo/machine/encoders.py
gordo/machine/loader.py
gordo/machine/machine.py
gordo/machine/validators.py
gordo/machine/metadata/__init__.py
gordo/machine/metadata/metadata.py
gordo/machine/model/__init__.py
gordo/machine/model/base.py
gordo/machine/model/models.py
gordo/machine/model/register.py
gordo/machine/model/utils.py
gordo/machine/model/anomaly/__init__.py
gordo/machine/model/anomaly/base.py
gordo/machine/model/anomaly/diff.py
gordo/machine/model/factories/__init__.py
gordo/machine/model/factories/feedforward_autoencoder.py
gordo/machine/model/factories/lstm_autoencoder.py
gordo/machine/model/factories/utils.py
gordo/machine/model/transformer_funcs/__init__.py
gordo/machine/model/transformer_funcs/general.py
gordo/machine/model/transformers/__init__.py
gordo/machine/model/transformers/imputer.py
gordo/reporters/__init__.py
gordo/reporters/base.py
gordo/reporters/exceptions.py
gordo/reporters/mlflow.py
gordo/reporters/postgres.py
gordo/serializer/__init__.py
gordo/serializer/from_definition.py
gordo/serializer/into_definition.py
gordo/serializer/serializer.py
gordo/serializer/utils.py
gordo/server/__init__.py
gordo/server/model_io.py
gordo/server/properties.py
gordo/server/server.py
gordo/server/utils.py
gordo/server/blueprints/__init__.py
gordo/server/blueprints/anomaly.py
gordo/server/blueprints/base.py
gordo/server/prometheus/__init__.py
gordo/server/prometheus/gunicorn_config.py
gordo/server/prometheus/metrics.py
gordo/server/prometheus/server.py
gordo/util/__init__.py
gordo/util/disk_registry.py
gordo/util/text.py
gordo/util/utils.py
gordo/util/version.py
gordo/workflow/__init__.py
gordo-6.0.4.dist-info/LICENSE
gordo-6.0.4.dist-info/METADATA
gordo-6.0.4.dist-info/WHEEL
gordo-6.0.4.dist-info/entry_points.txt
gordo-6.0.4.dist-info/top_level.txt
gordo-6.0.4.dist-info/zip-safe
gordo-6.0.4.dist-info/RECORD
